{
"meta":{"test_sets":[],"test_metrics":[],"learn_metrics":[{"best_value":"Min","name":"Logloss"}],"launch_mode":"Train","parameters":"","iteration_count":100,"learn_sets":["learn"],"name":"experiment"},
"iterations":[
{"learn":[0.5125330912],"iteration":0,"passed_time":0.002111310474,"remaining_time":0.2090197369},
{"learn":[0.4315369565],"iteration":1,"passed_time":0.004332759987,"remaining_time":0.2123052394},
{"learn":[0.3878028077],"iteration":2,"passed_time":0.00643397636,"remaining_time":0.2080319023},
{"learn":[0.359017327],"iteration":3,"passed_time":0.008580484598,"remaining_time":0.2059316303},
{"learn":[0.3429750055],"iteration":4,"passed_time":0.01078124434,"remaining_time":0.2048436425},
{"learn":[0.3303647422],"iteration":5,"passed_time":0.01300188059,"remaining_time":0.2036961292},
{"learn":[0.3214676898],"iteration":6,"passed_time":0.01514037905,"remaining_time":0.2011507502},
{"learn":[0.3164836432],"iteration":7,"passed_time":0.01737569523,"remaining_time":0.1998204951},
{"learn":[0.312394115],"iteration":8,"passed_time":0.01948555796,"remaining_time":0.1970206416},
{"learn":[0.307621879],"iteration":9,"passed_time":0.02176117829,"remaining_time":0.1958506046},
{"learn":[0.3044016536],"iteration":10,"passed_time":0.02404034017,"remaining_time":0.1945082068},
{"learn":[0.3016027298],"iteration":11,"passed_time":0.02637568546,"remaining_time":0.1934216934},
{"learn":[0.2995953596],"iteration":12,"passed_time":0.02855213161,"remaining_time":0.19107965},
{"learn":[0.2971443833],"iteration":13,"passed_time":0.03066743721,"remaining_time":0.1883856857},
{"learn":[0.2959147643],"iteration":14,"passed_time":0.03281955129,"remaining_time":0.1859774573},
{"learn":[0.2948508927],"iteration":15,"passed_time":0.03503041832,"remaining_time":0.1839096962},
{"learn":[0.2935419534],"iteration":16,"passed_time":0.03709300033,"remaining_time":0.1811011192},
{"learn":[0.2923903326],"iteration":17,"passed_time":0.03921506153,"remaining_time":0.1786463914},
{"learn":[0.2912719416],"iteration":18,"passed_time":0.04131054443,"remaining_time":0.1761133736},
{"learn":[0.2899795012],"iteration":19,"passed_time":0.04356050151,"remaining_time":0.174242006},
{"learn":[0.2875730897],"iteration":20,"passed_time":0.04570447132,"remaining_time":0.1719358683},
{"learn":[0.2868691202],"iteration":21,"passed_time":0.04784002103,"remaining_time":0.16961462},
{"learn":[0.2863635425],"iteration":22,"passed_time":0.05000206308,"remaining_time":0.1673982112},
{"learn":[0.2859905333],"iteration":23,"passed_time":0.05213525685,"remaining_time":0.16509498},
{"learn":[0.2851779219],"iteration":24,"passed_time":0.05435821475,"remaining_time":0.1630746443},
{"learn":[0.2845229622],"iteration":25,"passed_time":0.05650394137,"remaining_time":0.1608189101},
{"learn":[0.2839411656],"iteration":26,"passed_time":0.05870346223,"remaining_time":0.1587167682},
{"learn":[0.2835385753],"iteration":27,"passed_time":0.06084958651,"remaining_time":0.1564703653},
{"learn":[0.2828980681],"iteration":28,"passed_time":0.06309698249,"remaining_time":0.1544788192},
{"learn":[0.2824587858],"iteration":29,"passed_time":0.06534961037,"remaining_time":0.1524824242},
{"learn":[0.2816043889],"iteration":30,"passed_time":0.06751516866,"remaining_time":0.150275698},
{"learn":[0.2810144265],"iteration":31,"passed_time":0.06958379848,"remaining_time":0.1478655718},
{"learn":[0.280627096],"iteration":32,"passed_time":0.07162010333,"remaining_time":0.1454105128},
{"learn":[0.2798334015],"iteration":33,"passed_time":0.07380686509,"remaining_time":0.1432721499},
{"learn":[0.2790041421],"iteration":34,"passed_time":0.07593746928,"remaining_time":0.1410267287},
{"learn":[0.2782210622],"iteration":35,"passed_time":0.07821488174,"remaining_time":0.1390486787},
{"learn":[0.2778756126],"iteration":36,"passed_time":0.08038695565,"remaining_time":0.1368750867},
{"learn":[0.2776436166],"iteration":37,"passed_time":0.08253904125,"remaining_time":0.134668962},
{"learn":[0.2770673976],"iteration":38,"passed_time":0.0845579036,"remaining_time":0.1322572338},
{"learn":[0.2767905215],"iteration":39,"passed_time":0.08654991762,"remaining_time":0.1298248764},
{"learn":[0.2763558814],"iteration":40,"passed_time":0.08873998729,"remaining_time":0.1276990061},
{"learn":[0.27599651],"iteration":41,"passed_time":0.09086653991,"remaining_time":0.1254823646},
{"learn":[0.2756987426],"iteration":42,"passed_time":0.09300519923,"remaining_time":0.1232859618},
{"learn":[0.2752149815],"iteration":43,"passed_time":0.09510461081,"remaining_time":0.1210422319},
{"learn":[0.2748392256],"iteration":44,"passed_time":0.09713693477,"remaining_time":0.1187229203},
{"learn":[0.2744208103],"iteration":45,"passed_time":0.09933889385,"remaining_time":0.1166152232},
{"learn":[0.2738614633],"iteration":46,"passed_time":0.1016280623,"remaining_time":0.1146018575},
{"learn":[0.2735163297],"iteration":47,"passed_time":0.1037304743,"remaining_time":0.1123746805},
{"learn":[0.2730374416],"iteration":48,"passed_time":0.1059802584,"remaining_time":0.1103059832},
{"learn":[0.2729131868],"iteration":49,"passed_time":0.1079831734,"remaining_time":0.1079831734},
{"learn":[0.2718627693],"iteration":50,"passed_time":0.1101498583,"remaining_time":0.105830256},
{"learn":[0.2716290959],"iteration":51,"passed_time":0.1123531744,"remaining_time":0.1037106225},
{"learn":[0.2711582484],"iteration":52,"passed_time":0.1145066392,"remaining_time":0.1015436234},
{"learn":[0.2710216918],"iteration":53,"passed_time":0.1165374901,"remaining_time":0.09927267672},
{"learn":[0.2705779912],"iteration":54,"passed_time":0.1187594053,"remaining_time":0.09716678613},
{"learn":[0.270084278],"iteration":55,"passed_time":0.1211394454,"remaining_time":0.09518099282},
{"learn":[0.2698333306],"iteration":56,"passed_time":0.1237186472,"remaining_time":0.09333161102},
{"learn":[0.2695811174],"iteration":57,"passed_time":0.1259213531,"remaining_time":0.09118442808},
{"learn":[0.269388778],"iteration":58,"passed_time":0.128035106,"remaining_time":0.08897354821},
{"learn":[0.2692256081],"iteration":59,"passed_time":0.1301423949,"remaining_time":0.08676159663},
{"learn":[0.2689987786],"iteration":60,"passed_time":0.1322605417,"remaining_time":0.08456001846},
{"learn":[0.2686672164],"iteration":61,"passed_time":0.1344236138,"remaining_time":0.08238866651},
{"learn":[0.2682262262],"iteration":62,"passed_time":0.1365308105,"remaining_time":0.0801847617},
{"learn":[0.2680541655],"iteration":63,"passed_time":0.1386237402,"remaining_time":0.07797585384},
{"learn":[0.2677394796],"iteration":64,"passed_time":0.1408097889,"remaining_time":0.07582065554},
{"learn":[0.2675862105],"iteration":65,"passed_time":0.1429092764,"remaining_time":0.07361993026},
{"learn":[0.2671928331],"iteration":66,"passed_time":0.145128477,"remaining_time":0.07148119017},
{"learn":[0.2665615421],"iteration":67,"passed_time":0.1473150811,"remaining_time":0.06932474404},
{"learn":[0.2664045428],"iteration":68,"passed_time":0.1493583456,"remaining_time":0.06710302485},
{"learn":[0.2660335023],"iteration":69,"passed_time":0.1516169464,"remaining_time":0.06497869133},
{"learn":[0.2657509132],"iteration":70,"passed_time":0.1537665063,"remaining_time":0.06280603777},
{"learn":[0.265473944],"iteration":71,"passed_time":0.1558455804,"remaining_time":0.06060661459},
{"learn":[0.264825253],"iteration":72,"passed_time":0.1579717612,"remaining_time":0.05842791167},
{"learn":[0.2647049195],"iteration":73,"passed_time":0.1600658438,"remaining_time":0.05623935053},
{"learn":[0.2644093056],"iteration":74,"passed_time":0.16233238,"remaining_time":0.05411079334},
{"learn":[0.2642706945],"iteration":75,"passed_time":0.1644416278,"remaining_time":0.05192893509},
{"learn":[0.2640315057],"iteration":76,"passed_time":0.1667440073,"remaining_time":0.04980665154},
{"learn":[0.2637429585],"iteration":77,"passed_time":0.1689696297,"remaining_time":0.04765810069},
{"learn":[0.2635475098],"iteration":78,"passed_time":0.1711444282,"remaining_time":0.04549408851},
{"learn":[0.2634019103],"iteration":79,"passed_time":0.1734891424,"remaining_time":0.04337228561},
{"learn":[0.263314051],"iteration":80,"passed_time":0.1756339171,"remaining_time":0.04119807931},
{"learn":[0.2630473608],"iteration":81,"passed_time":0.1778958184,"remaining_time":0.0390503016},
{"learn":[0.262842791],"iteration":82,"passed_time":0.1801815312,"remaining_time":0.03690465098},
{"learn":[0.2624728318],"iteration":83,"passed_time":0.1823184412,"remaining_time":0.03472732212},
{"learn":[0.2623573323],"iteration":84,"passed_time":0.1843279884,"remaining_time":0.03252846854},
{"learn":[0.2621353579],"iteration":85,"passed_time":0.1863607849,"remaining_time":0.03033780219},
{"learn":[0.2618437723],"iteration":86,"passed_time":0.1885342164,"remaining_time":0.02817177946},
{"learn":[0.261616397],"iteration":87,"passed_time":0.1907132542,"remaining_time":0.02600635285},
{"learn":[0.2615481354],"iteration":88,"passed_time":0.1927745773,"remaining_time":0.02382607135},
{"learn":[0.2612322501],"iteration":89,"passed_time":0.1949843763,"remaining_time":0.0216649307},
{"learn":[0.260843633],"iteration":90,"passed_time":0.1972328123,"remaining_time":0.01950654188},
{"learn":[0.2605074161],"iteration":91,"passed_time":0.1994728299,"remaining_time":0.01734546347},
{"learn":[0.2604149569],"iteration":92,"passed_time":0.2014784537,"remaining_time":0.0151650449},
{"learn":[0.2603232537],"iteration":93,"passed_time":0.2035958273,"remaining_time":0.01299547834},
{"learn":[0.260143492],"iteration":94,"passed_time":0.2057253677,"remaining_time":0.01082765093},
{"learn":[0.2600278588],"iteration":95,"passed_time":0.2078973161,"remaining_time":0.008662388169},
{"learn":[0.2597397104],"iteration":96,"passed_time":0.2100500309,"remaining_time":0.006496392707},
{"learn":[0.2596294299],"iteration":97,"passed_time":0.2120979867,"remaining_time":0.004328530341},
{"learn":[0.2593545669],"iteration":98,"passed_time":0.2146514598,"remaining_time":0.002168196564},
{"learn":[0.2589894663],"iteration":99,"passed_time":0.2168517349,"remaining_time":0}
]}